lagrange_rmatrix/__init__.py
lagrange_rmatrix/__version__.py
lagrange_rmatrix/bloch_se.py
lagrange_rmatrix/lagrange_rmatrix.py
lagrange_rmatrix/potentials.py
lagrange_rmatrix/utils.py
lagrange_rmatrix-0.2.dist-info/LICENSE
lagrange_rmatrix-0.2.dist-info/METADATA
lagrange_rmatrix-0.2.dist-info/WHEEL
lagrange_rmatrix-0.2.dist-info/top_level.txt
lagrange_rmatrix-0.2.dist-info/RECORD
