Metadata-Version: 2.1
Name: lagrange-rmatrix
Version: 0.2
Summary: Solver for quantum scattering.
Author-email: Kyle Beyer <beykyle@umich.edu>
License: BSD 3-Clause License
Classifier: Programming Language :: Python :: 3
Classifier: License :: OSI Approved :: MIT License
Classifier: Operating System :: OS Independent
Requires-Python: >=3.9
License-File: LICENSE
Requires-Dist: numpy
Requires-Dist: scipy
Requires-Dist: mpmath
Requires-Dist: matplotlib
